{
  "build": "h464c3ec_0",
  "build_number": 0,
  "channel": "https://repo.anaconda.com/pkgs/main/win-64",
  "constrains": [],
  "depends": [
    "libiconv >=1.15,<2.0a0",
    "vc >=14.1,<15.0a0",
    "zlib >=1.2.11,<1.3.0a0"
  ],
  "features": "",
  "files": [
    "Library/bin/libxml2.dll",
    "Library/bin/runxmlconf.exe",
    "Library/bin/xmlcatalog.exe",
    "Library/bin/xmllint.exe",
    "Library/include/libxml/DOCBparser.h",
    "Library/include/libxml/HTMLparser.h",
    "Library/include/libxml/HTMLtree.h",
    "Library/include/libxml/SAX.h",
    "Library/include/libxml/SAX2.h",
    "Library/include/libxml/c14n.h",
    "Library/include/libxml/catalog.h",
    "Library/include/libxml/chvalid.h",
    "Library/include/libxml/debugXML.h",
    "Library/include/libxml/dict.h",
    "Library/include/libxml/encoding.h",
    "Library/include/libxml/entities.h",
    "Library/include/libxml/globals.h",
    "Library/include/libxml/hash.h",
    "Library/include/libxml/list.h",
    "Library/include/libxml/nanoftp.h",
    "Library/include/libxml/nanohttp.h",
    "Library/include/libxml/parser.h",
    "Library/include/libxml/parserInternals.h",
    "Library/include/libxml/pattern.h",
    "Library/include/libxml/relaxng.h",
    "Library/include/libxml/schemasInternals.h",
    "Library/include/libxml/schematron.h",
    "Library/include/libxml/threads.h",
    "Library/include/libxml/tree.h",
    "Library/include/libxml/uri.h",
    "Library/include/libxml/valid.h",
    "Library/include/libxml/xinclude.h",
    "Library/include/libxml/xlink.h",
    "Library/include/libxml/xmlIO.h",
    "Library/include/libxml/xmlautomata.h",
    "Library/include/libxml/xmlerror.h",
    "Library/include/libxml/xmlexports.h",
    "Library/include/libxml/xmlmemory.h",
    "Library/include/libxml/xmlmodule.h",
    "Library/include/libxml/xmlreader.h",
    "Library/include/libxml/xmlregexp.h",
    "Library/include/libxml/xmlsave.h",
    "Library/include/libxml/xmlschemas.h",
    "Library/include/libxml/xmlschemastypes.h",
    "Library/include/libxml/xmlstring.h",
    "Library/include/libxml/xmlunicode.h",
    "Library/include/libxml/xmlversion.h",
    "Library/include/libxml/xmlwriter.h",
    "Library/include/libxml/xpath.h",
    "Library/include/libxml/xpathInternals.h",
    "Library/include/libxml/xpointer.h",
    "Library/lib/libxml2.lib",
    "Library/lib/libxml2_a.lib",
    "Library/lib/libxml2_a_dll.lib"
  ],
  "fn": "libxml2-2.9.9-h464c3ec_0.tar.bz2",
  "installed_by": "Anaconda3-2019.03-Windows-x86_64.exe",
  "license": "MIT",
  "license_family": "MIT",
  "link": {
    "source": "C:\\Users\\MTXDevp\\Desktop\\PROYECTO-INTEGRADO\\ITRADE-API-LARAVEL-PROYECTO-INTEGRADO\\ITRADE-API\\resources\\python\\Conda\\pkgs\\libxml2-2.9.9-h464c3ec_0",
    "type": "hard-link"
  },
  "md5": "6ed19ec01f8b50c99b09e9134742a478",
  "name": "libxml2",
  "size": 3645712,
  "subdir": "win-64",
  "timestamp": 1547910808052,
  "track_features": "",
  "url": "https://repo.anaconda.com/pkgs/main/win-64/libxml2-2.9.9-h464c3ec_0.tar.bz2",
  "version": "2.9.9"
}